{
  "project_info": {
    "project_number": "829564958536",
    "project_id": "election-2021-82df9",
    "storage_bucket": "election-2021-82df9.appspot.com"
  },
  "client": [
    {
      "client_info": {
        "mobilesdk_app_id": "1:829564958536:android:25d28acc81ea7d5e8aa57d",
        "android_client_info": {
          "package_name": "com.hector.election_2021_user"
        }
      },
      "oauth_client": [
        {
          "client_id": "829564958536-lkqon5lmo8oj1qjk5mpmsehht7q97mjn.apps.googleusercontent.com",
          "client_type": 1,
          "android_info": {
            "package_name": "com.hector.election_2021_user",
            "certificate_hash": "66ebd46eef1a276c5ac6e7782b9a1514c0e83fc5"
          }
        },
        {
          "client_id": "829564958536-2issn9m7j28rs1g9uqk8eso5j9sd56ec.apps.googleusercontent.com",
          "client_type": 3
        }
      ],
      "api_key": [
        {
          "current_key": "AIzaSyDrtgbj8wyhKZeSLANvX8d9mWWMoKBLIb8"
        }
      ],
      "services": {
        "appinvite_service": {
          "other_platform_oauth_client": [
            {
              "client_id": "829564958536-2issn9m7j28rs1g9uqk8eso5j9sd56ec.apps.googleusercontent.com",
              "client_type": 3
            }
          ]
        }
      }
    }
  ],
  "configuration_version": "1"
}